setup.py
alertlogic/__init__.py
alertlogic/appliance.py
alertlogic/connection.py
alertlogic/host.py
alertlogic.egg-info/PKG-INFO
alertlogic.egg-info/SOURCES.txt
alertlogic.egg-info/dependency_links.txt
alertlogic.egg-info/top_level.txt
test/test_alert_logic.py