Metadata-Version: 1.1
Name: alertlogic
Version: 0.4.0
Summary: Alert Logic Library
Home-page: https://github.com/joekiller/alertlogic-python
Author: Joseph Lawson
Author-email: joe@joekiller.com
License: Apache v2.0
Platform: Posix; MacOS X; Windows
Classifier: Development Status :: 3 - Alpha
Classifier: Intended Audience :: Developers
Classifier: Intended Audience :: System Administrators
Classifier: License :: OSI Approved :: Apache Software License
Classifier: Operating System :: OS Independent
Classifier: Topic :: System :: Networking :: Monitoring
